{"alternativeNames":"Allorge-Boiteau, Lucile","comments":"Boiteau, Lucile","dates":"1937-2023","examples":"Apocynaceae subtribus Callichilinae L.Allorge in Bull. Mus. Nation. Hist. Nat.,  B, Adansonia 1983(2): 235. 1983.","forename":"Lucile","fqId":"urn:lsid:ipni.org:authors:35748-1","id":"35748-1","isoCountries":"France","recordType":"author","source":"IK db. Date from L.J. Dorr, Plant Collectors in Madagascar and the Comoro  Islands. Year of death from G.Rouhan (P).","standardForm":"L.Allorge","surname":"Allorge","suppressed":false,"taxonGroups":"Spermatophytes","url":"/a/35748-1","version":"1.3","summary":"Allorge, Lucile (1937-2023)","hasBhlLink":false}