{"alternativeNames":"","dates":"fl. 2005","examples":"Masdevallia munae Luer & R.Barrow in Monogr. Syst. Bot. Missouri Bot. Gard. 103: 291 (2005)","forename":"Roy","fqId":"urn:lsid:ipni.org:authors:20007141-1","id":"20007141-1","isoCountries":"","recordType":"author","source":"First name from p. 12 of publ. cited below.","standardForm":"R.Barrow","surname":"Barrow","suppressed":false,"taxonGroups":"Spermatophytes","url":"/a/20007141-1","version":"1.1.2.1","summary":"Barrow, Roy (fl. 2005)","hasBhlLink":false}