{"alternativeNames":"Prohens, J.","dates":"fl. 2006","examples":"Solanum perlongistylum G. J. Anderson, Martine, Prohens & Nuez, Novon 16(2): 162. 2006.","forename":"Jaime","fqId":"urn:lsid:ipni.org:authors:20007048-2","id":"20007048-2","isoCountries":"Spain","recordType":"author","source":"full name from: http://www.upv.es/pls/oalu/est_per.Info_Persona%3FP_NIP%3D1325%26p_e","standardForm":"Prohens","surname":"Prohens Tomás","suppressed":false,"taxonGroups":"Fossils, Spermatophytes","url":"/a/20007048-2","version":"1.1.2.1","summary":"Prohens Tomás, Jaime (fl. 2006)","hasBhlLink":false}