{"alternativeAbbreviations":"Leibl. From TL2","alternativeNames":"","dates":"fl. 1884","forename":"Otto","fqId":"urn:lsid:ipni.org:authors:5438-1","id":"5438-1","isoCountries":"","recordType":"author","standardForm":"Leibling","surname":"Leibling","suppressed":false,"taxonGroups":"Spermatophytes","url":"/a/5438-1","version":"1.1.1.1","summary":"Leibling, Otto (fl. 1884)","hasBhlLink":true,"bhlPageLink":"http://www.biodiversitylibrary.org/openurl?ctx_ver=Z39.88-2004&rft_id=http://www.biodiversitylibrary.org/page/33069067&rft_val_fmt=info:ofi/fmt:kev:mtx:book&url_ver=z39.88-2004"}