{"alternativeAbbreviations":"G.Lindsay From Meikle","alternativeNames":"","dates":"1916-2002","examples":"Mammillaria boolii G.E.Linds. in Cact. Succ. J. (Los Angeles) 25: 48. (1953)","forename":"George Edmund","fqId":"urn:lsid:ipni.org:authors:5623-1","id":"5623-1","isoCountries":"United States","recordType":"author","source":"Obit. in Cact. Succ. J. (Los Angeles), 75(3): 96-97 (2003)","standardForm":"G.E.Linds.","surname":"Lindsay","suppressed":false,"taxonGroups":"Spermatophytes","url":"/a/5623-1","version":"1.2","summary":"Lindsay, George Edmund (1916-2002)","hasBhlLink":false}