{"alternativeAbbreviations":"Litv. From Meikle;Litv. From TL2;Litw. From literature","alternativeNames":"Litwinow, Dmitrij Ivanovitsch","dates":"1854-1929","examples":"Dorema sabulosum Litv. in Sched. Herb. Fl. Ross. 8: 2 (1922).","forename":"Dimitri Ivanovich","fqId":"urn:lsid:ipni.org:authors:5663-1","id":"5663-1","isoCountries":"Russian Federation","recordType":"author","source":"CMI","standardForm":"Litv.","surname":"Litvinov","suppressed":false,"taxonGroups":"Mycology, Spermatophytes","url":"/a/5663-1","version":"1.2","summary":"Litvinov, Dimitri Ivanovich (1854-1929)","hasBhlLink":false}