{"alternativeNames":"","dates":"1849-1937","examples":"Yucca karlsruhensis Graebener, Mitt. Deutsch. Dendrol. Ges. 7. 1903","forename":"Leopold","fqId":"urn:lsid:ipni.org:authors:14007-1","id":"14007-1","isoCountries":"Germany","recordType":"author","source":"From Hortus Third, Liberty Hyde Hortorium, (1976); Dates in: Stadt Karlsruhe - zur Startseite ... Personen, https://stadtlexikon.karlsruhe.de/index.php/De:Lexikon:bio-1189 (via Boris Heuer)","standardForm":"Graebener","surname":"Graebener","suppressed":false,"taxonGroups":"Spermatophytes","url":"/a/14007-1","version":"1.2","summary":"Graebener, Leopold (1849-1937)","hasBhlLink":false}