{"alternativeNames":"Carnevali Fern치ndez-Concha, Germ치n","dates":"1955-","examples":"Octomeria gemmula G. Carnevali F.C. & I. Ramirez in Ernstia, 39: 13 (1986).","forename":"Germ치n","fqId":"urn:lsid:ipni.org:authors:14638-1","id":"14638-1","isoCountries":"Venezuela","notes":"https://orcid.org/0000-0002-2659-9352","recordType":"author","source":"from D.H. Kent 1990. Full name and date of birth from author via Gandhi (HUH).","standardForm":"Carnevali","surname":"Carnevali","suppressed":false,"taxonGroups":"Spermatophytes","url":"/a/14638-1","version":"1.2","summary":"Carnevali, Germ치n (1955-)","hasBhlLink":false}