{"alternativeNames":"","dates":"1929-","examples":"Achnanthes catenata Bily & Marvan in Preslia, 31: 34 (1959).  Calcarispora hiemalis Marvanová & Marvan in Cas. slezsk. Mus. Opave 12: 109 (1963)","forename":"Petr","fqId":"urn:lsid:ipni.org:authors:14824-1","id":"14824-1","isoCountries":"","recordType":"author","source":"Berkeley Algal List, CMI, from D.H. Kent 1990","standardForm":"Marvan","surname":"Marvan","suppressed":false,"taxonGroups":"Algae, Mycology","url":"/a/14824-1","version":"1.2","summary":"Marvan, Petr (1929-)","hasBhlLink":false}