{"alternativeNames":"Morris, John; Morris, Frank","comments":"Born in Scotland.","dates":"1869-1949","examples":"Habenaria albida (L.) R.Br. var. straminea (Fernald) F.J.A.Morris & E.A.Eames, Our Wild Orchids 69. 1929","forename":"Francis John A.","fqId":"urn:lsid:ipni.org:authors:14858-1","id":"14858-1","isoCountries":"Canada","recordType":"author","source":"from D.H. Kent 1990. http://www.mcelroy.ca/history/morris/","standardForm":"F.J.A.Morris","surname":"Morris","suppressed":false,"taxonGroups":"Spermatophytes","url":"/a/14858-1","version":"1.3.2.1","summary":"Morris, Francis John A. (1869-1949)","hasBhlLink":false}