{"alternativeNames":"","dates":"fl. 1991","examples":"Carex kitaibeliana var. capillata (Acht.) M.P. Stoeva, E.D. Popova & K.G.  Uzunova in S.I. Kozhukharov & B.A. Kuzmanov (eds.), Evolyutsiya Tsvet. Rast. i  Florogen., 2: 152 (1991). Carex humilis var. longifolia M.P. Stoeva & E.D. Popova in Folia Geobot.  Phytotax., 26(4): 392 (1991 publ. 1992).","forename":"Evgenija D.","fqId":"urn:lsid:ipni.org:authors:36082-1","id":"36082-1","isoCountries":"","recordType":"author","source":"IK db","standardForm":"E.D.Popova","surname":"Popova","suppressed":false,"taxonGroups":"Spermatophytes","url":"/a/36082-1","version":"1.1","summary":"Popova, Evgenija D. (fl. 1991)","hasBhlLink":false}