{"alternativeNames":"","dates":"1954-","examples":"Braya humilis subsp. ellesmerensis J.G. Harris, Novon 16(3): 345. 2006.","forename":"James G.","fqId":"urn:lsid:ipni.org:authors:20008578-2","id":"20008578-2","isoCountries":"United States","recordType":"author","source":"Birth year from Patricia K. Holmgren (NY)","standardForm":"J.G.Harris","surname":"Harris","suppressed":false,"taxonGroups":"Spermatophytes","url":"/a/20008578-2","version":"1.1.2.1","summary":"Harris, James G. (1954-)","hasBhlLink":false}