{"alternativeAbbreviations":"Coombe From Meikle","alternativeNames":"","dates":"1927-1999","examples":"Trifolium occidentale Coombe in Watsonia 5: 70 (1961).","forename":"David Edwin","fqId":"urn:lsid:ipni.org:authors:1786-1","id":"1786-1","isoCountries":"","recordType":"author","source":"Flora Europaea. Letter from A. Hansen 28 June 1982. Obituary in Watsonia, 23(2): 360-367 (2000).","standardForm":"Coombe","surname":"Coombe","suppressed":false,"taxonGroups":"Spermatophytes","url":"/a/1786-1","version":"1.1","summary":"Coombe, David Edwin (1927-1999)","hasBhlLink":false}