{"alternativeAbbreviations":"Crosswh. From Meikle","alternativeNames":"","dates":"1940-2008","examples":"Penstemon maguirei Crosswh. in Leafl. W. Bot. 10: 171. (1965)","forename":"Frank Samuel","fqId":"urn:lsid:ipni.org:authors:1890-1","id":"1890-1","isoCountries":"United States","recordType":"author","source":"Obit. in Desert Pl., 25(1): 16 (2009), incl. portr.","standardForm":"Crosswh.","surname":"Crosswhite","suppressed":false,"taxonGroups":"Spermatophytes","url":"/a/1890-1","version":"1.3","summary":"Crosswhite, Frank Samuel (1940-2008)","hasBhlLink":false}