{"alternativeAbbreviations":"D채niker From Meikle","alternativeNames":"Daeniker, Albert Ulrich","dates":"1894-1957","examples":"Sukkulentenkunde (Jahrb. Schweiz. Kakt. Ges) 2: 19 (1948)","forename":"Albert Ulrich","fqId":"urn:lsid:ipni.org:authors:1988-1","id":"1988-1","isoCountries":"","recordType":"author","source":"Pichi Sermolli's list, 3 March 1991","standardForm":"D채niker","surname":"D채niker","suppressed":false,"taxonGroups":"Spermatophytes, Pteridophytes","url":"/a/1988-1","version":"1.1","summary":"D채niker, Albert Ulrich (1894-1957)","hasBhlLink":false}