{"alternativeAbbreviations":"Bluket From Meikle","alternativeNames":"","dates":"fl. 1930","examples":"Ceratocarpus utriculosus Bluk. ex Krylov, Fl. Zapadnoi Sibiri, 4: 905 (1930).","forename":"N.A.","fqId":"urn:lsid:ipni.org:authors:870-1","id":"870-1","isoCountries":"","recordType":"author","source":"Publ. cited here.","standardForm":"Bluket","surname":"Bluket","suppressed":false,"taxonGroups":"Spermatophytes","url":"/a/870-1","version":"1.2","summary":"Bluket, N.A. (fl. 1930)","hasBhlLink":false}