{"alternativeNames":"Vázquez Pardo, Francisco María","dates":"1964-","examples":"Quercus x pacensis F.M. Vázquez in An. Jard. Bot. Madrid, 53(2): 249 (1995). Stipa clausa var. matritensis F.M.Vazquez & Devesa in An. Jard. Bot. Madrid, 54(1): 412 (1996).","forename":"Francisco María","fqId":"urn:lsid:ipni.org:authors:37121-1","id":"37121-1","isoCountries":"Spain","recordType":"author","source":"IK db.","standardForm":"F.M.Vázquez","surname":"Vázquez","suppressed":false,"taxonGroups":"Spermatophytes","url":"/a/37121-1","version":"1.1","summary":"Vázquez, Francisco María (1964-)","hasBhlLink":false}