{"alternativeNames":"","dates":"fl. 1995","examples":"Canna variegatifolia M.M. Ciciarelli in Rev. Mus. La Plata, Bot., 14(103): 334  (1995).","forename":"Maria de las Mercedes","fqId":"urn:lsid:ipni.org:authors:37743-1","id":"37743-1","isoCountries":"Argentina","recordType":"author","source":"IK db.","standardForm":"Ciciar.","surname":"Ciciarelli","suppressed":false,"taxonGroups":"Spermatophytes","url":"/a/37743-1","version":"1.1","summary":"Ciciarelli, Maria de las Mercedes (fl. 1995)","hasBhlLink":false}