{"alternativeNames":"","dates":"fl. 2013","examples":"Sporobolus nesiotioides Longhi-Wagner, R.J.V.Alves & N.G.Silva in Phytotaxa 144(1): 13. 2013","forename":"Nílber Gonçalves","fqId":"urn:lsid:ipni.org:authors:20024344-1","id":"20024344-1","isoCountries":"","notes":"http://orcid.org/0000-0002-2179-1898","recordType":"author","standardForm":"N.G.Silva","surname":"Da Silva","suppressed":false,"taxonGroups":"Spermatophytes","url":"/a/20024344-1","version":"1.4","summary":"Da Silva, Nílber Gonçalves (fl. 2013)","hasBhlLink":false}