{"alternativeAbbreviations":"K.Peterson From Meikle","alternativeNames":"","dates":"1948-2003","examples":"Hymenoclea salsola var. fasciculata (A.Nelson) K.M.Peterson & W.W.Payne in Brittonia, 25(3): 255 (1973).","forename":"Kathleen M.","fqId":"urn:lsid:ipni.org:authors:7576-1","id":"7576-1","isoCountries":"","recordType":"author","source":"Letter from A. Hansen c. 1984. J.Reveal 26 Jan. 2004.","standardForm":"K.M.Peterson","surname":"Peterson","suppressed":false,"taxonGroups":"Spermatophytes","url":"/a/7576-1","version":"1.1.2.1","summary":"Peterson, Kathleen M. (1948-2003)","hasBhlLink":false}