{"alternativeNames":"Pallithanam, Joseph","dates":"1915-1984","examples":"Indigofera karuppiana Pallith. in J. Bombay Nat. Hist. Soc., 73(1): 239 (1976).","forename":"Joseph Mathen","fqId":"urn:lsid:ipni.org:authors:39851-1","id":"39851-1","isoCountries":"India","recordType":"author","source":"IK db. K.M. Matthew.; GCI file","standardForm":"Pallith.","surname":"Pallithanam","suppressed":false,"taxonGroups":"Spermatophytes","url":"/a/39851-1","version":"1.1.2.1","summary":"Pallithanam, Joseph Mathen (1915-1984)","hasBhlLink":false}