{"alternativeNames":"","dates":"fl. 1994","examples":"Cortinarius citrinus var. paraionochlorus Cadiñanos & J.A. Muñoz in Cadiñanos Aguirre, Belarra (Bilbao) 10-11: 58. 1994.","forename":"José Antonio","fqId":"urn:lsid:ipni.org:authors:20003424-1","id":"20003424-1","isoCountries":"","recordType":"author","source":"IMI","standardForm":"J.A.Muñoz","surname":"Muñoz","suppressed":false,"taxonGroups":"Mycology","url":"/a/20003424-1","version":"1.2","summary":"Muñoz, José Antonio (fl. 1994)","hasBhlLink":false}