{"alternativeAbbreviations":"Stebler From TL2","alternativeNames":"","dates":"1852-1935","forename":"Friedrich Gottlieb","fqId":"urn:lsid:ipni.org:authors:10050-1","id":"10050-1","isoCountries":"","recordType":"author","standardForm":"Stebler","surname":"Stebler","suppressed":false,"taxonGroups":"Spermatophytes","url":"/a/10050-1","version":"1.1.1.1","summary":"Stebler, Friedrich Gottlieb (1852-1935)","hasBhlLink":true,"bhlPageLink":"http://www.biodiversitylibrary.org/openurl?ctx_ver=Z39.88-2004&rft_id=http://www.biodiversitylibrary.org/page/33333995&rft_val_fmt=info:ofi/fmt:kev:mtx:book&url_ver=z39.88-2004"}