{"alternativeAbbreviations":"Strecker From TL2","alternativeNames":"","dates":"1858-1934","forename":"Wilhelm","fqId":"urn:lsid:ipni.org:authors:10210-1","id":"10210-1","isoCountries":"","recordType":"author","standardForm":"Strecker","surname":"Strecker","suppressed":false,"taxonGroups":"Spermatophytes","url":"/a/10210-1","version":"1.1.1.1","summary":"Strecker, Wilhelm (1858-1934)","hasBhlLink":true,"bhlPageLink":"http://www.biodiversitylibrary.org/openurl?ctx_ver=Z39.88-2004&rft_id=http://www.biodiversitylibrary.org/page/33212048&rft_val_fmt=info:ofi/fmt:kev:mtx:book&url_ver=z39.88-2004"}