{"alternativeAbbreviations":"Swainson From TL2","alternativeNames":"","comments":"No record of having been an author of a plant name.","dates":"1789-1855","forename":"William","fqId":"urn:lsid:ipni.org:authors:10330-1","id":"10330-1","isoCountries":"","recordType":"author","standardForm":"Swainson","surname":"Swainson","suppressed":false,"taxonGroups":"Spermatophytes","url":"/a/10330-1","version":"1.2.1.1","summary":"Swainson, William (1789-1855)","hasBhlLink":true,"bhlPageLink":"http://www.biodiversitylibrary.org/openurl?ctx_ver=Z39.88-2004&rft_id=http://www.biodiversitylibrary.org/page/33212153&rft_val_fmt=info:ofi/fmt:kev:mtx:book&url_ver=z39.88-2004"}