{"alternativeAbbreviations":"T.Tang From TL2;Tsin Tang From Meikle","alternativeNames":"Tang, Jin; Tang, Chin","dates":"1897-1984","examples":"Corybas taliensis Tang & F.T. Wang in Acta Phytotax. Sin., 1: 185 (1951).","forename":"Tsin","fqId":"urn:lsid:ipni.org:authors:10418-1","id":"10418-1","isoCountries":"","recordType":"author","source":"Letter from A. Hansen 18.10.83. Index Herb. Sin.(1993). Bibliog. Chinese Syst.  Bot. (1949-1990)(1993). Merrill, E.D. & Walker, E.H., Bibliog. East. Asiatic  Bot.","standardForm":"Tang","surname":"Tang","suppressed":false,"taxonGroups":"Spermatophytes","url":"/a/10418-1","version":"1.2.1.1","summary":"Tang, Tsin (1897-1984)","hasBhlLink":true,"bhlPageLink":"http://www.biodiversitylibrary.org/openurl?ctx_ver=Z39.88-2004&rft_id=http://www.biodiversitylibrary.org/page/33212203&rft_val_fmt=info:ofi/fmt:kev:mtx:book&url_ver=z39.88-2004"}