{"alternativeAbbreviations":"Ter-Chatsch. From Meikle","alternativeNames":"","dates":"1902-","examples":"Sempervivum sosnowskyi Ter-Chatsch., Zametki Sist. Geogr. Rast. 13: 17 (1947)","forename":"Susanna Yakovlevna","fqId":"urn:lsid:ipni.org:authors:10518-1","id":"10518-1","isoCountries":"Georgia","recordType":"author","source":"Forename from: Alexander B. Doweld (IFPNI)","standardForm":"Ter-Chatsch.","surname":"Ter-Chatschaturova","suppressed":false,"taxonGroups":"Spermatophytes","url":"/a/10518-1","version":"1.2","summary":"Ter-Chatschaturova, Susanna Yakovlevna (1902-)","hasBhlLink":false}