{"alternativeAbbreviations":"R.Uechtr. From TL2;R.Uechtr. From Meikle","alternativeNames":"","dates":"1838-1886","forename":"Rudolf (Karl(Carl)) Friedrich von","fqId":"urn:lsid:ipni.org:authors:10952-1","id":"10952-1","isoCountries":"","recordType":"author","standardForm":"R.Uechtr.","surname":"Uechtritz","suppressed":false,"taxonGroups":"Spermatophytes","url":"/a/10952-1","version":"1.1.1.1","summary":"Uechtritz, Rudolf (Karl(Carl)) Friedrich von (1838-1886)","hasBhlLink":true,"bhlPageLink":"http://www.biodiversitylibrary.org/openurl?ctx_ver=Z39.88-2004&rft_id=http://www.biodiversitylibrary.org/page/33212604&rft_val_fmt=info:ofi/fmt:kev:mtx:book&url_ver=z39.88-2004"}