{"alternativeNames":"","dates":"1808-1882","examples":"Lychnis bicolor hort. ex Czerw. & L.Schwarz in Index Sem. [Cracow] 1875: 14. 1876","forename":"Ignacy Rafał","fqId":"urn:lsid:ipni.org:authors:20021657-1","id":"20021657-1","isoCountries":"","recordType":"author","source":"Document on Botanic Garden of the Jagiellonian University, Cracow","standardForm":"Czerw.","surname":"Czerwiakowski","suppressed":false,"taxonGroups":"Spermatophytes","url":"/a/20021657-1","version":"1.2","summary":"Czerwiakowski, Ignacy Rafał (1808-1882)","hasBhlLink":false}