{"alternativeNames":"","dates":"fl. 2005","examples":"Cuspidothrix P.Rajan, Komárek, Willame, Hrouzek, Kaštovská, L.Hoffm. & Sivonen in Algol. Stud. 117:  388. 2005.","forename":"Kaarina","fqId":"urn:lsid:ipni.org:authors:20013150-1","id":"20013150-1","isoCountries":"","recordType":"author","source":"R.Jahn & Kusber - AlgaTerra Information System (B)","standardForm":"Sivonen","surname":"Sivonen","suppressed":false,"taxonGroups":"Algae","url":"/a/20013150-1","version":"1.1","summary":"Sivonen, Kaarina (fl. 2005)","hasBhlLink":false}