{"alternativeAbbreviations":"J.Garden From Meikle","alternativeNames":"","dates":"1923-2018","examples":"Callitris monticola in Contrib. N.S. Wales Nat. Herb. ii. 385 (1957)","forename":"Joy","fqId":"urn:lsid:ipni.org:authors:3023-1","id":"3023-1","isoCountries":"Australia","notes":"after 1956, Thompson, Joy","recordType":"author","source":"from J. Thompson 7 March 1990","standardForm":"J.Garden","surname":"Garden","suppressed":false,"taxonGroups":"Spermatophytes","url":"/a/3023-1","version":"1.2","summary":"Garden, Joy (1923-2018)","hasBhlLink":false}