{"alternativeAbbreviations":"Gattef. From Meikle","alternativeNames":"","dates":"1899-1960","examples":"Chrysanthemum × schousboeanum Gattef. & Maire  Bull. Soc. Hist. Nat. Afrique N. xxxi. 107 (1941).","forename":"Jean","fqId":"urn:lsid:ipni.org:authors:3045-1","id":"3045-1","isoCountries":"","recordType":"author","source":"Year of death from R. Mogn.;  See http://tinyurl.com/bnhgbxv","standardForm":"Gattef.","surname":"Gattefossé","suppressed":false,"taxonGroups":"Spermatophytes","url":"/a/3045-1","version":"1.3","summary":"Gattefossé, Jean (1899-1960)","hasBhlLink":false}