{"alternativeAbbreviations":"Harkn. From Meikle","alternativeNames":"","comments":"Plant taxonomist with Monroe County Department of Parks, Rochester, New York, USA 1940s-1967.","dates":"1907-1980","examples":"Magnolia x slavinii B.E.Harkn. in Nat. Hort. Mag. Amer., 33: 118 (1954).","forename":"Bernard Emerson","fqId":"urn:lsid:ipni.org:authors:3659-1","id":"3659-1","isoCountries":"","recordType":"author","source":"Dates from Freek Vrugtman, International Lilac Registrar, RBG, Hamilton.","standardForm":"B.E.Harkn.","surname":"Harkness","suppressed":false,"taxonGroups":"Spermatophytes","url":"/a/3659-1","version":"1.2","summary":"Harkness, Bernard Emerson (1907-1980)","hasBhlLink":false}