{"alternativeAbbreviations":"Herre From TL2","alternativeNames":"","dates":"1868-1962","forename":"Albert William Christian Theodore","fqId":"urn:lsid:ipni.org:authors:3883-1","id":"3883-1","isoCountries":"United States","recordType":"author","source":"CMI","standardForm":"Herre","surname":"Herre","suppressed":false,"taxonGroups":"Mycology","url":"/a/3883-1","version":"1.1.1.1","summary":"Herre, Albert William Christian Theodore (1868-1962)","hasBhlLink":true,"bhlPageLink":"http://www.biodiversitylibrary.org/openurl?ctx_ver=Z39.88-2004&rft_id=http://www.biodiversitylibrary.org/page/33068416&rft_val_fmt=info:ofi/fmt:kev:mtx:book&url_ver=z39.88-2004"}