{"alternativeAbbreviations":"E.Hitchc. From TL2;Hitchc. From Meikle","alternativeNames":"","dates":"1793-1864","examples":"'M' example: Gyropodium (1825). 'P' example: Botrychium simplex E.Hitchc. Amer. J. Sci. Arts 6: 103, t. 8. (1823)","forename":"Edward","fqId":"urn:lsid:ipni.org:authors:3973-1","id":"3973-1","isoCountries":"","recordType":"author","source":"CMI, from R.E.G.Pichi Sermolli 1 March 1991","standardForm":"E.Hitchc.","surname":"Hitchcock","suppressed":false,"taxonGroups":"Pteridophytes, Spermatophytes, Mycology","url":"/a/3973-1","version":"1.2.1.1","summary":"Hitchcock, Edward (1793-1864)","hasBhlLink":true,"bhlPageLink":"http://www.biodiversitylibrary.org/openurl?ctx_ver=Z39.88-2004&rft_id=http://www.biodiversitylibrary.org/page/33068459&rft_val_fmt=info:ofi/fmt:kev:mtx:book&url_ver=z39.88-2004"}