{"alternativeNames":"","dates":"fl. 2014","examples":"Dioscorea sphaeroidea R.Couto & J.M.A.Braga in Phytotaxa 163(4): 230. 2014","forename":"Ricardo Sousa","fqId":"urn:lsid:ipni.org:authors:20026340-1","id":"20026340-1","isoCountries":"","notes":"https://orcid.org/0000-0002-9992-1496","recordType":"author","standardForm":"R.Couto","surname":"Couto","suppressed":false,"taxonGroups":"Spermatophytes","url":"/a/20026340-1","version":"1.2","summary":"Couto, Ricardo Sousa (fl. 2014)","hasBhlLink":false}