{"alternativeNames":"Sierra, Rubén","comments":"Lichenologist.","dates":"1983-","examples":"Neoechinodiscus Molinari & R.Sierra in Opuscula Philolichenum 19: 172–173. 2020.","forename":"Rubén","fqId":"urn:lsid:ipni.org:authors:20058382-1","id":"20058382-1","isoCountries":"Peru","recordType":"author","source":"Birth year & full name from: Eduardo Antonio Molinari Novoa (AlgaeBase)","standardForm":"R.Sierra","surname":"Sierra Tintaya","suppressed":false,"taxonGroups":"Mycology","url":"/a/20058382-1","version":"1.4","summary":"Sierra Tintaya, Rubén (1983-)","hasBhlLink":false}