{"alternativeAbbreviations":"Rawitscher From TL2","alternativeNames":"","dates":"1890-1957","forename":"Felix","fqId":"urn:lsid:ipni.org:authors:8187-1","id":"8187-1","isoCountries":"","recordType":"author","standardForm":"Rawitscher","surname":"Rawitscher","suppressed":false,"taxonGroups":"Spermatophytes","url":"/a/8187-1","version":"1.1.1.1","summary":"Rawitscher, Felix (1890-1957)","hasBhlLink":true,"bhlPageLink":"http://www.biodiversitylibrary.org/openurl?ctx_ver=Z39.88-2004&rft_id=http://www.biodiversitylibrary.org/page/33190074&rft_val_fmt=info:ofi/fmt:kev:mtx:book&url_ver=z39.88-2004"}