{"alternativeAbbreviations":"Rothmayr From TL2","alternativeNames":"","dates":"fl. 1910","forename":"Julius","fqId":"urn:lsid:ipni.org:authors:8649-1","id":"8649-1","isoCountries":"Switzerland","recordType":"author","standardForm":"Rothmayr","surname":"Rothmayr","suppressed":false,"taxonGroups":"Mycology","url":"/a/8649-1","version":"1.1.1.1","summary":"Rothmayr, Julius (fl. 1910)","hasBhlLink":true,"bhlPageLink":"http://www.biodiversitylibrary.org/openurl?ctx_ver=Z39.88-2004&rft_id=http://www.biodiversitylibrary.org/page/33190398&rft_val_fmt=info:ofi/fmt:kev:mtx:book&url_ver=z39.88-2004"}