{"alternativeAbbreviations":"Fenn. From Meikle","alternativeNames":"","comments":"Published Drawing Room Botany 1840.  Also zoologist.","dates":"fl. 1840","forename":"James Hamilton","fqId":"urn:lsid:ipni.org:authors:2681-1","id":"2681-1","isoCountries":"","recordType":"author","source":"Letter from G. Buchheim 12 Apr. 1989. R. Desmond, Dict. Brit. & Irish Botanists & Hort. (1994)","standardForm":"J.H.Fennell","surname":"Fennell","suppressed":false,"taxonGroups":"Spermatophytes","url":"/a/2681-1","version":"1.1","summary":"Fennell, James Hamilton (fl. 1840)","hasBhlLink":false}