{"alternativeAbbreviations":"Fliche From TL2","alternativeNames":"","dates":"1836-1908","forename":"Paul Henri Maria Thérèse André","fqId":"urn:lsid:ipni.org:authors:2784-1","id":"2784-1","isoCountries":"France","recordType":"author","source":"Berkeley Algal List; Pichi Sermolli's list, 3 March 1991 from H.t.Clifford's list of Palaeobotanists","standardForm":"Fliche","surname":"Fliche","suppressed":false,"taxonGroups":"Fossils, Algae, Pteridophytes","url":"/a/2784-1","version":"1.1","summary":"Fliche, Paul Henri Maria Thérèse André (1836-1908)","hasBhlLink":false}