{"alternativeAbbreviations":"Floret From Meikle","alternativeNames":"","dates":"1939-","examples":"Comiphyton J.J. Floret in Adansonia, 14(3): 501 (1974).","forename":"Jean-Jacques","fqId":"urn:lsid:ipni.org:authors:2789-1","id":"2789-1","isoCountries":"France","recordType":"author","source":"Index Herbariorum, ed. 8. L.J. Dorr, Plant Collectors of Madagascar and the  Comoro Islands: 157 (1997).","standardForm":"Floret","surname":"Floret","suppressed":false,"taxonGroups":"Spermatophytes","url":"/a/2789-1","version":"1.1","summary":"Floret, Jean-Jacques (1939-)","hasBhlLink":false}