{"alternativeNames":"Tenorio Lezama, Pedro","dates":"fl. 1997","examples":"Cunila crenata M.R. Garcia-Pena & P. Tenorio Lezama in An. Inst. Biol. Univ.  Nac. Autón. Mex., Bot., 68(1): 2 (1997).","forename":"Pedro","fqId":"urn:lsid:ipni.org:authors:38250-1","id":"38250-1","isoCountries":"","recordType":"author","source":"IK db.","standardForm":"Tenorio","surname":"Tenorio","suppressed":false,"taxonGroups":"Spermatophytes","url":"/a/38250-1","version":"1.1","summary":"Tenorio, Pedro (fl. 1997)","hasBhlLink":false}