{"alternativeAbbreviations":"L.Watson From Meikle","alternativeNames":"","dates":"1938-","examples":"Kew Bull., 18:  (1965)","forename":"Leslie","fqId":"urn:lsid:ipni.org:authors:11435-1","id":"11435-1","isoCountries":"","recordType":"author","source":"Letter from H.T. Clifford 9 May 1988 from D.H.Kent 19 March 1991","standardForm":"L.Watson","surname":"Watson","suppressed":false,"taxonGroups":"Spermatophytes","url":"/a/11435-1","version":"1.1","summary":"Watson, Leslie (1938-)","hasBhlLink":false}