{"alternativeAbbreviations":"Wyatt-Smith From Meikle","alternativeNames":"","dates":"1917-2002","examples":"Calophyllum incrassatum M.R.Hend. & Wyatt-Sm. in Gard. Bull. Singapore, 15: 302 (1956)","forename":"John","fqId":"urn:lsid:ipni.org:authors:11911-1","id":"11911-1","isoCountries":"","recordType":"author","source":"Fl. Males. Bull., 13(3): 268 (2003).","standardForm":"Wyatt-Sm.","surname":"Wyatt-Smith","suppressed":false,"taxonGroups":"Spermatophytes","url":"/a/11911-1","version":"1.1.2.1","summary":"Wyatt-Smith, John (1917-2002)","hasBhlLink":false}