{"alternativeNames":"","dates":"fl. 2016","examples":"Parengyodontium C.C. Tsang, J.F.W. Chan, W.M. Pong, J.H.K. Chen, A.H.Y. Ngan, M. Cheung, C.K.C. Lai, D.N.C. Tsang, S.K.P. Lau & P.C.Y. Woo 2016","forename":"Mei","fqId":"urn:lsid:ipni.org:authors:20039387-1","id":"20039387-1","isoCountries":"","recordType":"author","source":"Index Fungorum","standardForm":"M.Cheung","surname":"Cheung","suppressed":false,"taxonGroups":"Mycology","url":"/a/20039387-1","version":"1.1","summary":"Cheung, Mei (fl. 2016)","hasBhlLink":false}