{"alternativeNames":"","dates":"1959-","examples":"Absconditella baegasanensis Lőkös, S.Y. Kondr. & Hur, Acta bot. hung. 55(3-4): 277 (2013)","forename":"László (S.)","fqId":"urn:lsid:ipni.org:authors:20039176-1","id":"20039176-1","isoCountries":"Hungary","notes":"Eponymy: Loekoesia S.Y. Kondr., S.O. Oh & Hur, in Mycobiology 43(3): 198 (2015)","recordType":"author","source":"Index Fungorum; Birth year from the GCI file","standardForm":"Lőkös","surname":"Lőkös","suppressed":false,"taxonGroups":"Mycology","url":"/a/20039176-1","version":"1.3","summary":"Lőkös, László (S.) (1959-)","hasBhlLink":false}