{"alternativeNames":"","dates":"fl. 2010","examples":"Fusarium mexicanum T. Aoki, S. Freeman, Otero-Colina, Rodr.-Alv., Fern.-Pavía, R.C. Ploetz & O'Donnell 2010","forename":"Gerardo","fqId":"urn:lsid:ipni.org:authors:20038426-1","id":"20038426-1","isoCountries":"","recordType":"author","source":"Index Fungorum","standardForm":"Rodr.-Alv.","surname":"Rodríguez-Alvarado","suppressed":false,"taxonGroups":"Mycology","url":"/a/20038426-1","version":"1.1","summary":"Rodríguez-Alvarado, Gerardo (fl. 2010)","hasBhlLink":false}