{"alternativeAbbreviations":"L.G.Silva From Rodriguésia 58(2): 399. 2007.","alternativeNames":"Silva, Luciana Fernandes Gomes da; Silva, Luciana Fernandes da","dates":"fl. 2007","examples":"Tachigali densiflora (Benth.) L.F.Gomes da Silva & H. C. Lima, Rodriguésia 58(2): 399. 2007.","forename":"Luciana Fernandes","fqId":"urn:lsid:ipni.org:authors:20012361-1","id":"20012361-1","isoCountries":"Brazil","recordType":"author","standardForm":"L.F.Gomes da Silva","surname":"Gomes da Silva","suppressed":false,"taxonGroups":"Spermatophytes","url":"/a/20012361-1","version":"1.2","summary":"Gomes da Silva, Luciana Fernandes (fl. 2007)","hasBhlLink":false}