{"alternativeNames":"Pugnaire, Francisco Ignacio","dates":"fl. 1989","examples":"Capparis ovata subsp. sicula (Veillard) Pugnaire in Blancoana, 7: 121 (1989)","forename":"Francisco Ignacio","fqId":"urn:lsid:ipni.org:authors:20012057-1","id":"20012057-1","isoCountries":"Spain","recordType":"author","source":"Publ. cited below.","standardForm":"Pugnaire","surname":"Pugnaire de Iraola","suppressed":false,"taxonGroups":"Spermatophytes","url":"/a/20012057-1","version":"1.1","summary":"Pugnaire de Iraola, Francisco Ignacio (fl. 1989)","hasBhlLink":false}