{"alternativeNames":"","dates":"1921-1996","examples":"Lilium gazarubrum Roane & J.N. Henry, Quart. Bull. N. Amer. Lily Soc. 34(1): 28 (1980). Endothiella viridistroma Roane, Chestnut blight, other Endothia diseases, and the genus Endothia (St. Paul): 35 (1986)","forename":"Martha Ann Kotila","fqId":"urn:lsid:ipni.org:authors:25649-1","id":"25649-1","isoCountries":"United States","recordType":"author","source":"CMI; Biography in: Virginia J. Sci. 47: 301-303. 1996 (via John E. Williams)","standardForm":"Roane","surname":"Roane","suppressed":false,"taxonGroups":"Spermatophytes, Mycology","url":"/a/25649-1","version":"1.2","summary":"Roane, Martha Ann Kotila (1921-1996)","hasBhlLink":false}