{"alternativeNames":"Urriés, Manuel Jordán de; Jordan, Manuel; Urriés y Azara, Manuel Jordán de; Urries, M.J.de; de Urries de Azara, M.J.","dates":"1909-1962","examples":"Trematosphaeria canariensis Urries in An. Inst. Bot. A.J.Cavanilles, 14: 162 (1956)","forename":"Manuel Jordan de","fqId":"urn:lsid:ipni.org:authors:28097-1","id":"28097-1","isoCountries":"Spain","recordType":"author","source":"CMI; Biography in: Anales Inst. Bot. Cavanilles 21(2): 331-336. 1962 (via Lotte Burkhardt; B)","standardForm":"Urries","surname":"Urries","suppressed":false,"taxonGroups":"Mycology","url":"/a/28097-1","version":"1.4","summary":"Urries, Manuel Jordan de (1909-1962)","hasBhlLink":false}