{"alternativeNames":"","dates":"fl. 1942-1989","examples":"Tribus Lysianeae Cocucci & Ventur., Bol. Soc. Argent. Bot. 21(1–4): 139 (1982).","forename":"Margarida","fqId":"urn:lsid:ipni.org:authors:28318-1","id":"28318-1","isoCountries":"Argentina","recordType":"author","source":"IK; Biography in: Bol. Soc. Argent. Bot. 26(3-4): 268. 1990 (via Lotte Burkhardt, B)","standardForm":"Ventur.","surname":"Venturelli","suppressed":false,"taxonGroups":"Spermatophytes","url":"/a/28318-1","version":"1.2","summary":"Venturelli, Margarida (fl. 1942-1989)","hasBhlLink":false}