{"alternativeNames":"","dates":"fl. 1990","examples":"Jubula himalayensis S.C.Srivast. et D.Sharma, Proceedings of the Indian Academy of Sciences. Plant Sciences 100: 85. 1990","forename":"Deepak","fqId":"urn:lsid:ipni.org:authors:20016204-1","id":"20016204-1","isoCountries":"","recordType":"author","source":"ELPT","standardForm":"D.Sharma","surname":"Sharma","suppressed":false,"taxonGroups":"Bryophytes","url":"/a/20016204-1","version":"1.2","summary":"Sharma, Deepak (fl. 1990)","hasBhlLink":false}