{"alternativeNames":"","dates":"fl. 2014","examples":"Cinnamomum mathewianum Remya Kr., E.S.S.Kumar, Radhamany, Valsalad. & R.Jagad., Int. J. Advanced Res. 2(7): 29. 2014 (epublished)","forename":"G.","fqId":"urn:lsid:ipni.org:authors:20016250-2","id":"20016250-2","isoCountries":"India","recordType":"author","standardForm":"Valsalad.","surname":"Valsaladevi","suppressed":false,"taxonGroups":"Spermatophytes","url":"/a/20016250-2","version":"1.1","summary":"Valsaladevi, G. (fl. 2014)","hasBhlLink":false}