{"alternativeNames":"","dates":"fl. 1981","examples":"Schiffneriolejeunea nymannii (Steph.) Gradst. et Terken, Occasional Papers of the Farlow Herbarium of Cryptogamic Botany 16: 79. 1981","forename":"Lucie","fqId":"urn:lsid:ipni.org:authors:20016174-1","id":"20016174-1","isoCountries":"","recordType":"author","source":"ELPT","standardForm":"Terken","surname":"Terken","suppressed":false,"taxonGroups":"Bryophytes","url":"/a/20016174-1","version":"1.1","summary":"Terken, Lucie (fl. 1981)","hasBhlLink":false}