{"alternativeAbbreviations":"Hull From TL2;Hull From Meikle","alternativeNames":"","dates":"1761-1843","forename":"John","fqId":"urn:lsid:ipni.org:authors:4217-1","id":"4217-1","isoCountries":"United Kingdom","recordType":"author","source":"Missouri Bryological List","standardForm":"Hull","surname":"Hull","suppressed":false,"taxonGroups":"Bryophytes","url":"/a/4217-1","version":"1.1.1.1","summary":"Hull, John (1761-1843)","hasBhlLink":true,"bhlPageLink":"http://www.biodiversitylibrary.org/openurl?ctx_ver=Z39.88-2004&rft_id=http://www.biodiversitylibrary.org/page/33068602&rft_val_fmt=info:ofi/fmt:kev:mtx:book&url_ver=z39.88-2004"}