{"alternativeAbbreviations":"Jameson From Meikle;W.Jameson From TL2","alternativeNames":"Jameson, Gulielmus; Jameson (of Quito), William","comments":"Author of Syn. Pl. aequator. (1865).","dates":"1796-1873","forename":"William","fqId":"urn:lsid:ipni.org:authors:4415-1","id":"4415-1","isoCountries":"Greenland, Ecuador, United Kingdom","recordType":"author","source":"R.W. Kiger, 17 April 1991. Obit. in Trans. & Proc. Bot. Soc. Edinb., 12: 19-28 (1876).","standardForm":"Jameson","surname":"Jameson","suppressed":false,"taxonGroups":"Spermatophytes","url":"/a/4415-1","version":"1.1.1.1","summary":"Jameson, William (1796-1873)","hasBhlLink":true,"bhlPageLink":"http://www.biodiversitylibrary.org/openurl?ctx_ver=Z39.88-2004&rft_id=http://www.biodiversitylibrary.org/page/33068663&rft_val_fmt=info:ofi/fmt:kev:mtx:book&url_ver=z39.88-2004"}