{"alternativeAbbreviations":"Kem.-Nat. From Meikle","alternativeNames":"Kemularia Natadze, Liubov Manucharovna; Kemularia-Nathadze, Luba","dates":"1891-1985","examples":"Dianthus subaggregatus Schischk. ex Kem.-Nath. in Monit. Jard. Bot. Tiflis, 1928-30, n. s. Pt. 5, 12 (1931).","forename":"Liubov Manucharovna","fqId":"urn:lsid:ipni.org:authors:4722-1","id":"4722-1","isoCountries":"","recordType":"author","source":"A. Hansen 27 March 1987. Zametki Sist. Geogr. Rast., 44-45: 5-7 (2004) in Georgian, incl. portr.","standardForm":"Kem.-Nath.","surname":"Kemularia-Nathadze","suppressed":false,"taxonGroups":"Spermatophytes","url":"/a/4722-1","version":"1.2","summary":"Kemularia-Nathadze, Liubov Manucharovna (1891-1985)","hasBhlLink":false}