{"alternativeNames":"Ros Espín, Rosa; Ros Espín, Rosa María","dates":"1959-","examples":"Weissia condensa var. armata (Thér. & Trab.) M.J.Cano, Ros & J.Guerra","forename":"Rosa María","fqId":"urn:lsid:ipni.org:authors:15660-1","id":"15660-1","isoCountries":"Spain","recordType":"author","source":"Missouri Bryological list updates Nov. 1990.  Full name from Marshall Crosby; Date from GCI file","standardForm":"Ros","surname":"Ros","suppressed":false,"taxonGroups":"Bryophytes","url":"/a/15660-1","version":"1.2.2.1","summary":"Ros, Rosa María (1959-)","hasBhlLink":false}