{"alternativeNames":"","dates":"1954-","examples":"'S' example: Orchidaceae Habenaria pectinata D.Don var. arietina (Hook.f.) R.C.Srivast. Nation. Acad. Sci. Letters 18(3–4): 61 (1995):.","forename":"Ramesh Chandra","fqId":"urn:lsid:ipni.org:authors:27105-1","id":"27105-1","isoCountries":"India","recordType":"author","source":"CMI. Forenames and date from P.Lakshminarasimhan.","standardForm":"R.C.Srivast.","surname":"Srivastava","suppressed":false,"taxonGroups":"Spermatophytes, Mycology","url":"/a/27105-1","version":"1.2","summary":"Srivastava, Ramesh Chandra (1954-)","hasBhlLink":false}