{"alternativeNames":"","dates":"fl. 1988","examples":"X Nopalxalis S端pplie in Succulenta 67(6): 141 (1988).","forename":"Frank","fqId":"urn:lsid:ipni.org:authors:27368-1","id":"27368-1","isoCountries":"","recordType":"author","source":"IK; Forename in: Cact. Succ. J. (Los Angeles) 77(5): 256-261. 2005 (via E.A. Molinari-Novoa)","standardForm":"S端pplie","surname":"S端pplie","suppressed":false,"taxonGroups":"Spermatophytes","url":"/a/27368-1","version":"1.2.2.2","summary":"S端pplie, Frank (fl. 1988)","hasBhlLink":false}