{"alternativeAbbreviations":"Tripp From TL2","alternativeNames":"","dates":"fl. 1868","forename":"Frances E","fqId":"urn:lsid:ipni.org:authors:27919-1","id":"27919-1","isoCountries":"United Kingdom","recordType":"author","source":"Missouri Bryological list","standardForm":"Tripp","surname":"Tripp","suppressed":false,"taxonGroups":"Bryophytes","url":"/a/27919-1","version":"1.2.1.1","summary":"Tripp, Frances E (fl. 1868)","hasBhlLink":true,"bhlPageLink":"http://www.biodiversitylibrary.org/openurl?ctx_ver=Z39.88-2004&rft_id=http://www.biodiversitylibrary.org/page/33212539&rft_val_fmt=info:ofi/fmt:kev:mtx:book&url_ver=z39.88-2004"}