{"alternativeNames":"","dates":"fl. 1860","examples":"Cactaceae Mammillaria severinii Regel & Klein bis Index Seminum [St. Petersburg] (1860) 46.","forename":"Eduard Petrowitsch","fqId":"urn:lsid:ipni.org:authors:20018649-1","id":"20018649-1","isoCountries":"","recordType":"author","source":"Publ. cited here; full name in Mitteilungen des Russischen Gartenbauvereins, St. Petersburg, Heft 1, 1859 und Heft 2, 1860","standardForm":"Klein bis","surname":"Klein","suppressed":false,"taxonGroups":"Spermatophytes","url":"/a/20018649-1","version":"1.2","summary":"Klein, Eduard Petrowitsch (fl. 1860)","hasBhlLink":false}