{"alternativeNames":"","dates":"fl. 2014","examples":"Gambierdiscus silvae S.Fraga & F.Rodr., Protist 165: 850. 2014","forename":"Francisco","fqId":"urn:lsid:ipni.org:authors:20018500-2","id":"20018500-2","isoCountries":"Spain","recordType":"author","source":"Author's name info from Paul W. Gabrielson (NCU)","standardForm":"F.Rodr.","surname":"Rodríguez","suppressed":false,"taxonGroups":"Algae","url":"/a/20018500-2","version":"1.1.2.2","summary":"Rodríguez, Francisco (fl. 2014)","hasBhlLink":false}