{"alternativeNames":"","dates":"fl. 1903","examples":"Aptosimum neglectum Emil Weber Bull. Herb. Boissier Ser. 2,. 3:. 894. (1903).","forename":"Emil","fqId":"urn:lsid:ipni.org:authors:20018648-1","id":"20018648-1","isoCountries":"","recordType":"author","source":"J.C.  Solomon.  See also, Die Gattungen Aptosimum Burch. und Peliostomum E. Mey. preprinted 15 Sep 1906 from Beih. Bot. Centralbl., Abt. 2., 21(2): 1-101 (1907).","standardForm":"Emil Weber","surname":"Weber","suppressed":false,"taxonGroups":"Spermatophytes","url":"/a/20018648-1","version":"1.1","summary":"Weber, Emil (fl. 1903)","hasBhlLink":false}