{"alternativeNames":"Mandujano, María","dates":"fl. 2003","examples":"Opuntia engelmannii subsp. aciculata (Griffiths) U.Guzmán & Mandujano in Cactaceae Syst. Inititatives, 16: 18 (2003)","forename":"María del C.","fqId":"urn:lsid:ipni.org:authors:20000137-1","id":"20000137-1","isoCountries":"","recordType":"author","source":"IK db.","standardForm":"Mandujano","surname":"Mandujano Sánchez","suppressed":false,"taxonGroups":"Spermatophytes","url":"/a/20000137-1","version":"1.3","summary":"Mandujano Sánchez, María del C. (fl. 2003)","hasBhlLink":false}