{"alternativeNames":"","dates":"1933-1997","examples":"Zoophthora gloeospora (Vuill.) A. Batko, Bull. Acad. Polon. Sci., Cl. II. sér. sci. biol. 12: 406 (1964)","forename":"Andrzej","fqId":"urn:lsid:ipni.org:authors:20000097-2","id":"20000097-2","isoCountries":"","recordType":"author","source":"Index Herb. ed.8. Z. Mirek et al., Kto Jest Kim W Botanice Polskiej: 17 (1995), incl. portr.; Death year in GCI and Index Fungorum","standardForm":"A.Batko","surname":"Batko","suppressed":false,"taxonGroups":"Mycology","url":"/a/20000097-2","version":"1.1.2.1","summary":"Batko, Andrzej (1933-1997)","hasBhlLink":false}