{"alternativeNames":"Sychak, N.N.; Sychak, N.M.","dates":"1967-","examples":"Alchemilla bucovinensis Sytschak, Ukrayins'k. Bot. Zhurn. 49(6): 99 .1992..","forename":"Nadiya N.","fqId":"urn:lsid:ipni.org:authors:20000080-2","id":"20000080-2","isoCountries":"","recordType":"author","source":"IK db.; author provided year of birth & correct spelling of names","standardForm":"Sytschak","surname":"Sytschak","suppressed":false,"taxonGroups":"Spermatophytes","url":"/a/20000080-2","version":"1.2","summary":"Sytschak, Nadiya N. (1967-)","hasBhlLink":false}