{"alternativeNames":"","dates":"fl. 2002","examples":"Lydenburgia abbottii (A.E.van Wyk & Prins) Steenkamp, A.E.van Wyk & Prins in Coates Palgrave, Trees S. Africa, ed. 3: 19 (2002)","forename":"Yolande","fqId":"urn:lsid:ipni.org:authors:20000094-1","id":"20000094-1","isoCountries":"","recordType":"author","source":"IK db.","standardForm":"Steenkamp","surname":"Steenkamp","suppressed":false,"taxonGroups":"Spermatophytes","url":"/a/20000094-1","version":"1.2.2.1","summary":"Steenkamp, Yolande (fl. 2002)","hasBhlLink":false}