{"alternativeNames":"Colom Casanovas, Guillem; Colom, Guillermo","dates":"1900-1993","examples":"Fibrosphaera minutissima Colom (1935)","forename":"Guillermo","fqId":"urn:lsid:ipni.org:authors:32782-1","id":"32782-1","isoCountries":"Spain","recordType":"author","source":"Berkeley Algal list; B.Valdes 2 January 1991; Biography in: Real Academia de la Historia, Diccionario Biográfico electrónico (DB~e), https://dbe.rah.es/biografias/37140/guillem-colom-casasnovas (via Eduardo Antonio Molinari Novoa; AlgaeBase)","standardForm":"Colom","surname":"Colom Casanovas","suppressed":false,"taxonGroups":"Fossils, Algae","url":"/a/32782-1","version":"1.2","summary":"Colom Casanovas, Guillermo (1900-1993)","hasBhlLink":false}