{"alternativeAbbreviations":"Schack From Meikle;Schack From TL2","alternativeNames":"","dates":"1878-1946","forename":"Hans Woldemar","fqId":"urn:lsid:ipni.org:authors:9001-1","id":"9001-1","isoCountries":"","recordType":"author","source":"Biography including portrait  and sample of signature in Willdenowia, 29(1-2): 337-348 (1999).","standardForm":"Schack","surname":"Schack","suppressed":false,"taxonGroups":"Spermatophytes","url":"/a/9001-1","version":"1.1.1.1","summary":"Schack, Hans Woldemar (1878-1946)","hasBhlLink":true,"bhlPageLink":"http://www.biodiversitylibrary.org/openurl?ctx_ver=Z39.88-2004&rft_id=http://www.biodiversitylibrary.org/page/33333240&rft_val_fmt=info:ofi/fmt:kev:mtx:book&url_ver=z39.88-2004"}