{"alternativeAbbreviations":"Cä.Schaeff From TL2","alternativeNames":"","dates":"1867-1944","forename":"Cäsar","fqId":"urn:lsid:ipni.org:authors:9003-1","id":"9003-1","isoCountries":"","recordType":"author","standardForm":"C.Schaeff.","surname":"Schaeffer","suppressed":false,"taxonGroups":"Spermatophytes","url":"/a/9003-1","version":"1.1.1.1","summary":"Schaeffer, Cäsar (1867-1944)","hasBhlLink":true,"bhlPageLink":"http://www.biodiversitylibrary.org/openurl?ctx_ver=Z39.88-2004&rft_id=http://www.biodiversitylibrary.org/page/33333243&rft_val_fmt=info:ofi/fmt:kev:mtx:book&url_ver=z39.88-2004"}