{"alternativeAbbreviations":"Scherfel From TL2","alternativeNames":"","dates":"1835-1895","forename":"Aurel Wilhelm (Vilmos Aurél)","fqId":"urn:lsid:ipni.org:authors:9058-1","id":"9058-1","isoCountries":"","recordType":"author","standardForm":"Scherfel","surname":"Scherfel","suppressed":false,"taxonGroups":"Spermatophytes","url":"/a/9058-1","version":"1.1.1.1","summary":"Scherfel, Aurel Wilhelm (Vilmos Aurél) (1835-1895)","hasBhlLink":true,"bhlPageLink":"http://www.biodiversitylibrary.org/openurl?ctx_ver=Z39.88-2004&rft_id=http://www.biodiversitylibrary.org/page/33333279&rft_val_fmt=info:ofi/fmt:kev:mtx:book&url_ver=z39.88-2004"}