{"alternativeAbbreviations":"F.Schmidt From Meikle;Friedr.Schmi From TL2","alternativeNames":"Schmidt, of St.Petersberg","dates":"1832-1908","forename":"Friedrich (Karl) (Fedor Bogdanovich)","fqId":"urn:lsid:ipni.org:authors:9159-1","id":"9159-1","isoCountries":"","recordType":"author","standardForm":"F.Schmidt","surname":"Schmidt","suppressed":false,"taxonGroups":"Spermatophytes","url":"/a/9159-1","version":"1.1","summary":"Schmidt, Friedrich (Karl) (Fedor Bogdanovich) (1832-1908)","hasBhlLink":false}