{"alternativeAbbreviations":"Schorler From TL2","alternativeNames":"","dates":"1859-1920","forename":"Bernhard","fqId":"urn:lsid:ipni.org:authors:9234-1","id":"9234-1","isoCountries":"","recordType":"author","source":"Berkeley Algal List","standardForm":"Schorler","surname":"Schorler","suppressed":false,"taxonGroups":"Algae","url":"/a/9234-1","version":"1.1.1.1","summary":"Schorler, Bernhard (1859-1920)","hasBhlLink":true,"bhlPageLink":"http://www.biodiversitylibrary.org/openurl?ctx_ver=Z39.88-2004&rft_id=http://www.biodiversitylibrary.org/page/33333442&rft_val_fmt=info:ofi/fmt:kev:mtx:book&url_ver=z39.88-2004"}