{"alternativeAbbreviations":"Schuler From TL2","alternativeNames":"","dates":"1853-1946","forename":"Johann Alois Ernst","fqId":"urn:lsid:ipni.org:authors:9287-1","id":"9287-1","isoCountries":"Austria","recordType":"author","source":"Missouri Bryological List","standardForm":"Schuler","surname":"Schuler","suppressed":false,"taxonGroups":"Mycology","url":"/a/9287-1","version":"1.1.1.1","summary":"Schuler, Johann Alois Ernst (1853-1946)","hasBhlLink":true,"bhlPageLink":"http://www.biodiversitylibrary.org/openurl?ctx_ver=Z39.88-2004&rft_id=http://www.biodiversitylibrary.org/page/33333504&rft_val_fmt=info:ofi/fmt:kev:mtx:book&url_ver=z39.88-2004"}