{"alternativeAbbreviations":"Smitin. From Meikle","alternativeNames":"","dates":"1920-1995","examples":"Shorea rogersiana Raiz. & Smitinand in Thai Forest Bull., Bot., 1: 7 (1954).","forename":"Tem","fqId":"urn:lsid:ipni.org:authors:9825-1","id":"9825-1","isoCountries":"Thailand","recordType":"author","source":"Index Herbariorum. IK. Date of death from Fl. Males. Bull., 11(7):497 (1996).","standardForm":"Smitinand","surname":"Smitinand","suppressed":false,"taxonGroups":"Spermatophytes","url":"/a/9825-1","version":"1.1","summary":"Smitinand, Tem (1920-1995)","hasBhlLink":false}