{"alternativeAbbreviations":"Sobol. From TL2;Sobol. From Meikle","alternativeNames":"Sobolewski, Gregor Fedorovitch (Grigoriy Fedorowich)","dates":"1741-1807","examples":"Mucor albus.","forename":"Gregor Fedorovitch (Grigoriy Fedorowich)","fqId":"urn:lsid:ipni.org:authors:9849-1","id":"9849-1","isoCountries":"","recordType":"author","source":"Mycological example from IMI.","standardForm":"Sobol.","surname":"Sobolewsky","suppressed":false,"taxonGroups":"Mycology, Spermatophytes","url":"/a/9849-1","version":"1.1","summary":"Sobolewsky, Gregor Fedorovitch (Grigoriy Fedorowich) (1741-1807)","hasBhlLink":false}