{"alternativeNames":"","dates":"fl. 2021","examples":"Hydrangea fistulosa (G.H.Huang & G.Hao) U.B.Deshmukh & M.B.Shende in Phytotaxa 512(2): 125. 2021.","forename":"Mukund Bapurao","fqId":"urn:lsid:ipni.org:authors:20047263-1","id":"20047263-1","isoCountries":"","notes":"https://orcid.org/0000-0003-0406-6886","recordType":"author","standardForm":"M.B.Shende","surname":"Shende","suppressed":false,"taxonGroups":"Spermatophytes","url":"/a/20047263-1","version":"1.1","summary":"Shende, Mukund Bapurao (fl. 2021)","hasBhlLink":false}