{"alternativeAbbreviations":"Maleev From Meikle","alternativeNames":"","dates":"1894-1941","examples":"Campanula komarovi Maleev Bull. Jard. Bot. Princ. URSS 29: 424 (1930).","forename":"Vladimir Petrovic","fqId":"urn:lsid:ipni.org:authors:6026-1","id":"6026-1","isoCountries":"Russian Federation","recordType":"author","standardForm":"Maleev","surname":"Maleev","suppressed":false,"taxonGroups":"Spermatophytes","url":"/a/6026-1","version":"1.2","summary":"Maleev, Vladimir Petrovic (1894-1941)","hasBhlLink":false}