{"alternativeAbbreviations":"M.Martens From Meikle;M.Martens From TL2","alternativeNames":"","dates":"1797-1863","forename":"Martin","fqId":"urn:lsid:ipni.org:authors:6150-1","id":"6150-1","isoCountries":"","recordType":"author","source":"from B.Parris' fern index","standardForm":"M.Martens","surname":"Martens","suppressed":false,"taxonGroups":"Pteridophytes, Spermatophytes","url":"/a/6150-1","version":"1.1.1.1","summary":"Martens, Martin (1797-1863)","hasBhlLink":true,"bhlPageLink":"http://www.biodiversitylibrary.org/openurl?ctx_ver=Z39.88-2004&rft_id=http://www.biodiversitylibrary.org/page/33355404&rft_val_fmt=info:ofi/fmt:kev:mtx:book&url_ver=z39.88-2004"}