{"alternativeAbbreviations":"Mendonça From Meikle;Mendonça From TL2","alternativeNames":"","dates":"1889-1982","forename":"Francisco de Ascencão","fqId":"urn:lsid:ipni.org:authors:6347-1","id":"6347-1","isoCountries":"Mozambique, Angola, Portugal","recordType":"author","source":"Letter from A. Hansen 23.4.86 from Pichi Sermolli 1 March 1991","standardForm":"Mendonça","surname":"Mendonça","suppressed":false,"taxonGroups":"Spermatophytes, Pteridophytes","url":"/a/6347-1","version":"1.1","summary":"Mendonça, Francisco de Ascencão (1889-1982)","hasBhlLink":false}