{"alternativeAbbreviations":"Mey.-Abich From TL2","alternativeNames":"","dates":"1893-","forename":"Adolf","fqId":"urn:lsid:ipni.org:authors:6420-1","id":"6420-1","isoCountries":"","recordType":"author","standardForm":"Mey.-Abich","surname":"Meyer-Abich","suppressed":false,"taxonGroups":"Spermatophytes","url":"/a/6420-1","version":"1.1.1.1","summary":"Meyer-Abich, Adolf (1893-)","hasBhlLink":true,"bhlPageLink":"http://www.biodiversitylibrary.org/openurl?ctx_ver=Z39.88-2004&rft_id=http://www.biodiversitylibrary.org/page/33355537&rft_val_fmt=info:ofi/fmt:kev:mtx:book&url_ver=z39.88-2004"}