{"alternativeNames":"","dates":"1918-2013","examples":"Helminthosporites mohgaoense Chitaley & M.T.Sheikh [as 'Helminthosoporites'], J. Indian bot. Soc. 50(2): 141. 1971","forename":"Shyamala D.","fqId":"urn:lsid:ipni.org:authors:17195-1","id":"17195-1","isoCountries":"India","recordType":"author","source":"H.T. Clifford's list of palaeobotanists; CMI; Forename & Dates in: Amer. J. Bot. 100(9): 1851. 2013 (via Lotte Burkhardt)","standardForm":"Chitaley","surname":"Chitaley","suppressed":false,"taxonGroups":"Mycology, Spermatophytes, Fossils","url":"/a/17195-1","version":"1.1.2.1","summary":"Chitaley, Shyamala D. (1918-2013)","hasBhlLink":false}