{"alternativeNames":"Fonseca Vaz, A.M.S.da; da Fonseca-Vaz, A.M.S.","dates":"1948-","examples":"Bauhinia grazielae in Atas Soc. Bot. Brasil, Secc. Rio de Janeiro 2(9): 74. 1984.","forename":"Angela Maria Studart da Fonseca","fqId":"urn:lsid:ipni.org:authors:17622-1","id":"17622-1","isoCountries":"Brazil","notes":"https://orcid.org/0000-0003-1475-9563","recordType":"author","source":"IK; GCI file, DOB correction from author via email","standardForm":"Vaz","surname":"Vaz","suppressed":false,"taxonGroups":"Spermatophytes","url":"/a/17622-1","version":"1.1.2.2.1.2","summary":"Vaz, Angela Maria Studart da Fonseca (1948-)","hasBhlLink":false}