{"alternativeNames":"","dates":"fl. 1986","examples":"Sahnia; Prostanthera arapilensis M.L.Williams, Drinnan & N.G.Walsh in Austral. Syst. Bot. 19(5): 475 (2006).","forename":"Andrew N.","fqId":"urn:lsid:ipni.org:authors:33996-1","id":"33996-1","isoCountries":"","recordType":"author","source":"H.T. Clifford's list of Palaeobotanists. First name from Austral. Syst. Bot. 19(5): 467 (2006).","standardForm":"Drinnan","surname":"Drinnan","suppressed":false,"taxonGroups":"Spermatophytes, Fossils","url":"/a/33996-1","version":"1.2","summary":"Drinnan, Andrew N. (fl. 1986)","hasBhlLink":false}