{"alternativeNames":"","dates":"fl. 2012","examples":"Bullera vrieseae Landell, L.R. Brandão, Safar, F.C.O. Gomes, C.R. Félix, A.R.O. Santos, D.M. Pagani, J.P. Ramos, Broetto, T. Mott, Vainstein, P. Valente & C.A. Rosa 2012","forename":"Danielle M.","fqId":"urn:lsid:ipni.org:authors:20036219-1","id":"20036219-1","isoCountries":"","recordType":"author","source":"Index Fungorum","standardForm":"D.M.Pagani","surname":"Pagani","suppressed":false,"taxonGroups":"Mycology","url":"/a/20036219-1","version":"1.1","summary":"Pagani, Danielle M. (fl. 2012)","hasBhlLink":false}