{"alternativeNames":"","dates":"1980-","examples":"Ctenitis bigarellae Schwartsb., Labiak & Salino, Brittonia 59(1): 29. 2007.","forename":"Pedro Bond","fqId":"urn:lsid:ipni.org:authors:20009077-2","id":"20009077-2","isoCountries":"Brazil","recordType":"author","source":"Publ. cited below. Date from author.","standardForm":"Schwartsb.","surname":"Schwartsburd","suppressed":false,"taxonGroups":"Pteridophytes","url":"/a/20009077-2","version":"1.3","summary":"Schwartsburd, Pedro Bond (1980-)","hasBhlLink":false}