{"alternativeNames":"Zamaloa, Maria del Carmen","dates":"1951-","examples":"Reboulisporites Zamaloa & E.J.Romero, Palynology 14: 126. 1990","forename":"Maria Carmen","fqId":"urn:lsid:ipni.org:authors:20017479-2","id":"20017479-2","isoCountries":"Argentina","recordType":"author","source":"Name information from Anders Hagborg (F)","standardForm":"Zamaloa","surname":"Zamaloa","suppressed":false,"taxonGroups":"Fossils","url":"/a/20017479-2","version":"1.1.2.1","summary":"Zamaloa, Maria Carmen (1951-)","hasBhlLink":false}